waybackmachine/__init__.py
waybackmachine/_archive_calls.py
waybackmachine/_common.py
waybackmachine/browse.py
waybackmachine/fetch.py
waybackmachine-0.5.0.dist-info/LICENSE
waybackmachine-0.5.0.dist-info/METADATA
waybackmachine-0.5.0.dist-info/WHEEL
waybackmachine-0.5.0.dist-info/top_level.txt
waybackmachine-0.5.0.dist-info/RECORD
