Metadata-Version: 2.1
Name: waybackmachine
Version: 0.5.0
Summary: Envelope for archive.org API.
Home-page: UNKNOWN
Author: Martin Beneš
Author-email: martinbenes1996@gmail.com
License: MPL
Project-URL: Homepage, https://pypi.org/project/waybackmachine/
Project-URL: Source, https://github.com/martinbenes1996/waybackmachine
Keywords: waybackmachine,archive,web,html,webscraping
Platform: UNKNOWN
Classifier: Development Status :: 4 - Beta
Classifier: Intended Audience :: Science/Research
Classifier: Intended Audience :: Developers
Classifier: Intended Audience :: Education
Classifier: Intended Audience :: Information Technology
Classifier: Intended Audience :: Other Audience
Classifier: Environment :: Web Environment
Classifier: Topic :: Scientific/Engineering
Classifier: Topic :: Scientific/Engineering :: Information Analysis
Classifier: Topic :: Software Development :: Libraries
Classifier: Topic :: Software Development :: Libraries :: Python Modules
Classifier: Topic :: Utilities
Classifier: License :: OSI Approved :: Mozilla Public License 2.0 (MPL 2.0)
Classifier: Programming Language :: Python :: 3
License-File: LICENSE
Requires-Dist: requests
